{"repo": {"timestamp": 1637757103000, "version": 20001, "name": "onionshare/onionshare-android-nightly", "icon": "icon.png", "address": "https://github.com/onionshare/onionshare-android-nightly/raw/master/fdroid/repo", "description": "Nightly builds from grote@fa41bac86477", "mirrors": ["https://raw.githubusercontent.com/onionshare/onionshare-android-nightly/master/fdroid/repo"]}, "requests": {"install": [], "uninstall": []}, "apps": [{"authorName": "onionshare-android-nightly", "authorWebSite": "https://github.com/onionshare", "categories": ["nightly"], "suggestedVersionCode": "1637757013", "description": "Nightly build of onionshare/onionshare-android", "issueTracker": "https://github.com/onionshare/onionshare-android/issues", "license": "Unknown", "sourceCode": "https://github.com/onionshare/onionshare-android", "summary": "Nightly build of onionshare/onionshare-android", "added": 1637625600000, "icon": "org.onionshare.android.nightly.1637757013.png", "packageName": "org.onionshare.android.nightly", "lastUpdated": 1637757099000, "localized": {"en-US": {"name": "OnionShare Nightly"}}}], "packages": {"org.onionshare.android.nightly": [{"added": 1637757099000, "apkName": "org.onionshare.android.nightly_1637757013.apk", "hash": "dd4e3dd35276d7defd325358bb271b318080ab683aa64a3926445bed0adef02c", "hashType": "sha256", "minSdkVersion": 21, "packageName": "org.onionshare.android.nightly", "sig": "115dbf01b274156b333ac411a2e371a9", "signer": "188d49fae21a7cc03fa35d001658fb85155343b54eabf0afd98644c017ab2d82", "size": 11882333, "targetSdkVersion": 31, "uses-permission": [["android.permission.INTERNET", null], ["android.permission.ACCESS_NETWORK_STATE", null], ["android.permission.ACCESS_WIFI_STATE", null], ["android.permission.FOREGROUND_SERVICE", null], ["android.permission.WAKE_LOCK", null]], "versionCode": 1637757013, "versionName": "0.1 (dc32ff8)"}, {"added": 1637625600000, "apkName": "org.onionshare.android.nightly_1637701731.apk", "hash": "899d84f4415f0972c250742f4cea983a05efaac7e4db1d41d4c801a1224323c4", "hashType": "sha256", "minSdkVersion": 21, "packageName": "org.onionshare.android.nightly", "sig": "d55c6fc6877cc87d7fa7f09dcd760209", "signer": "7e04f902940a2aedac30e491a5ce7adcc74a3f73b43459e4448222f3eee629ef", "size": 10850363, "targetSdkVersion": 31, "uses-permission": [["android.permission.INTERNET", null], ["android.permission.ACCESS_NETWORK_STATE", null], ["android.permission.ACCESS_WIFI_STATE", null], ["android.permission.FOREGROUND_SERVICE", null], ["android.permission.WAKE_LOCK", null]], "versionCode": 1637701731, "versionName": "0.1 (1041df6)"}, {"added": 1637625600000, "apkName": "org.onionshare.android.nightly_1637700605.apk", "hash": "8ec4fd2236701ff0a82aad74038f7cb766e50a99d405cabedf75a78aaaaadf4c", "hashType": "sha256", "minSdkVersion": 21, "packageName": "org.onionshare.android.nightly", "sig": "d55c6fc6877cc87d7fa7f09dcd760209", "signer": "7e04f902940a2aedac30e491a5ce7adcc74a3f73b43459e4448222f3eee629ef", "size": 10850368, "targetSdkVersion": 31, "uses-permission": [["android.permission.INTERNET", null], ["android.permission.ACCESS_NETWORK_STATE", null], ["android.permission.ACCESS_WIFI_STATE", null], ["android.permission.FOREGROUND_SERVICE", null], ["android.permission.WAKE_LOCK", null]], "versionCode": 1637700605, "versionName": "0.1 (830b53d)"}]}}